lightning_parser_overlays/__init__.py
lightning_parser_overlays/core.py
lightning_parser_overlays/goes_overlays.py
lightning_parser_overlays-0.3.51.dist-info/licenses/LICENSE
lightning_parser_overlays-0.3.51.dist-info/METADATA
lightning_parser_overlays-0.3.51.dist-info/WHEEL
lightning_parser_overlays-0.3.51.dist-info/top_level.txt
lightning_parser_overlays-0.3.51.dist-info/RECORD
