Metadata-Version: 2.4
Name: lightning_parser_overlays
Version: 0.3.51
Summary: Connor's Lightning Parser Overlays (LPO) is an overlay generation utility for different sensors onto the Lightning Parser Lib (LPL).
Author-email: Connor White <connor.sw.personal@gmail.com>
License-Expression: MIT
Project-URL: Homepage, https://github.com/CorniiDog/lightning_parser_overlays
Project-URL: Issues, https://github.com/CorniiDog/lightning_parser_overlays/issues
Classifier: Programming Language :: Python :: 3
Classifier: Operating System :: OS Independent
Requires-Python: >=3.9
License-File: LICENSE
Requires-Dist: pyproj
Requires-Dist: pandas
Requires-Dist: plotly
Requires-Dist: kaleido
Requires-Dist: scipy
Requires-Dist: tqdm
Requires-Dist: numpy
Requires-Dist: imageio
Requires-Dist: process-managerial
Requires-Dist: remote-events
Requires-Dist: datashader
Requires-Dist: matplotlib
Requires-Dist: holoviews
Requires-Dist: geopandas
Requires-Dist: Deprecation
Requires-Dist: MetPy
Requires-Dist: goes
Dynamic: license-file
